chameleonpricing/__init__.py
chameleonpricing/price_calculator.py
chameleonpricing-1.0.0.dist-info/METADATA
chameleonpricing-1.0.0.dist-info/WHEEL
chameleonpricing-1.0.0.dist-info/top_level.txt
chameleonpricing-1.0.0.dist-info/RECORD
