Metadata-Version: 2.1
Name: chameleonpricing
Version: 1.0.0
Summary: Price recommender system for SAAS companies
Home-page: https://github.com/mikelvallejo/chameleon-pricing
Author: mikelvallejo
Author-email: mikelvallejo9@gmail.com
License: UNKNOWN
Platform: UNKNOWN
Classifier: Programming Language :: Python :: 3
Classifier: License :: OSI Approved :: MIT License
Classifier: Operating System :: OS Independent
